<?xml version="1.0" encoding="UTF-8"?><record_update table="oauth_entity">
    <oauth_entity action="INSERT_OR_UPDATE">
        <access>public</access>
        <access_token_lifespan>1800</access_token_lifespan>
        <active>true</active>
        <auth_code_lifespan>60</auth_code_lifespan>
        <auth_url/>
        <certificate_url/>
        <client_id>07d17b1ac2744db9b3bc6f9d3ed7928a</client_id>
        <client_secret>﷞﷟﷒c83805508321e650f257f3a6feaad317﷬﷔1﷬﷭TQi_SjAABErKx6FL6Suo9Q==HzvMYtyiGUkxv28NjtEIxLoF3wOCLEExilU=﷮﷯</client_secret>
        <client_type/>
        <client_uuid>cde4b0668325a290f257f3a6feaad3ef</client_uuid>
        <code_challenge_method>S256</code_challenge_method>
        <comments/>
        <default_grant_type>password</default_grant_type>
        <extend_refresh_token_expiry>false</extend_refresh_token_expiry>
        <id_token_lifespan>86400</id_token_lifespan>
        <jwt_provider/>
        <login_url/>
        <logo_url/>
        <message_signature_lifespan>60</message_signature_lifespan>
        <mobile_client>false</mobile_client>
        <name>Github</name>
        <oauth_api_script/>
        <protocol_name/>
        <public_client>false</public_client>
        <redirect_url/>
        <refresh_token_lifespan>8640000</refresh_token_lifespan>
        <refresh_token_url/>
        <restricted_binding>false</restricted_binding>
        <revoke_token_url/>
        <salt/>
        <send_client_credentials_as>request_body_parameter</send_client_credentials_as>
        <skip_authorize>false</skip_authorize>
        <sys_class_name>oauth_entity</sys_class_name>
        <sys_created_by>admin</sys_created_by>
        <sys_created_on>2025-05-19 08:40:51</sys_created_on>
        <sys_id>01e4b0668325a290f257f3a6feaad3f0</sys_id>
        <sys_mod_count>0</sys_mod_count>
        <sys_name>Github</sys_name>
        <sys_package display_value="Pletra Asset Management" source="x_1734342_pletra_0">e2238c7b83c12210f257f3a6feaad35d</sys_package>
        <sys_policy/>
        <sys_scope display_value="Pletra Asset Management">e2238c7b83c12210f257f3a6feaad35d</sys_scope>
        <sys_update_name>oauth_entity_01e4b0668325a290f257f3a6feaad3f0</sys_update_name>
        <sys_updated_by>admin</sys_updated_by>
        <sys_updated_on>2025-05-19 08:40:51</sys_updated_on>
        <token_url/>
        <type>client</type>
        <use_mutual_auth>false</use_mutual_auth>
        <user/>
    </oauth_entity>
</record_update>
